demo_package_041320pt/__init__.py
demo_package_041320pt/demo_package_041320pt.py
demo_package_041320pt/lz.py
demo_package_041320pt/my_functions.py
demo_package_041320pt-0.1.1.dist-info/AUTHORS.rst
demo_package_041320pt-0.1.1.dist-info/LICENSE
demo_package_041320pt-0.1.1.dist-info/METADATA
demo_package_041320pt-0.1.1.dist-info/WHEEL
demo_package_041320pt-0.1.1.dist-info/top_level.txt
demo_package_041320pt-0.1.1.dist-info/RECORD
