Metadata-Version: 2.1
Name: demo-package-041320pt
Version: 0.1.1
Summary: Demo package for class
Home-page: https://github.com/jirvingphd/demo_package_041320pt
Author: James Irving
Author-email: james.irving@flatironschool.com
License: GNU General Public License v3
Keywords: demo_package_041320pt
Platform: UNKNOWN
Classifier: Development Status :: 2 - Pre-Alpha
Classifier: Intended Audience :: Developers
Classifier: License :: OSI Approved :: GNU General Public License v3 (GPLv3)
Classifier: Natural Language :: English
Classifier: Programming Language :: Python :: 3
Classifier: Programming Language :: Python :: 3.5
Classifier: Programming Language :: Python :: 3.6
Classifier: Programming Language :: Python :: 3.7
Classifier: Programming Language :: Python :: 3.8
Requires-Python: >=3.5
